COPYING
MANIFEST.in
README.md
setup.py
plyj/__init__.py
plyj/model.py
plyj/parser.py
plyj.egg-info/PKG-INFO
plyj.egg-info/SOURCES.txt
plyj.egg-info/dependency_links.txt
plyj.egg-info/requires.txt
plyj.egg-info/top_level.txt