Metadata-Version: 1.1
Name: plyj
Version: 0.1
Summary: A Java parser written in Python using PLY. 
Home-page: http://github.com/musiKk/plyj
Author: Werner Hahn
Author-email: werner_hahn@gmx.com
License: COPYING
Platform: UNKNOWN
Classifier: Development Status :: 4 - Beta
Classifier: Intended Audience :: Developers
Classifier: Intended Audience :: Education
Classifier: Intended Audience :: Science/Research
Classifier: Operating System :: OS Independent
Classifier: Programming Language :: Python
Classifier: Topic :: Education
Classifier: Topic :: Software Development
Classifier: Topic :: Software Development :: Libraries
Classifier: Topic :: Software Development :: Libraries :: Python Modules
Classifier: Topic :: Text Processing
